question 3/johnson.v
module johnson_counter (
    input wire clock,
    input wire reset,
    output wire [3:0] counter_state
);

reg [3:0] counter;

always @(posedge clock or posedge reset) begin
    if (reset)
        counter <= 4'b0000;
    else
        counter <= {counter[2:0], ~counter[3]};
end

assign counter_state = counter;

endmodule

question 3/johnson_tb.v
`timescale 1ns/1ns
`include "johnson.v"




module johnson_counter_tb;

reg clock;
reg reset;
wire [3:0] counter_state;

// Instantiate the Johnson counter module
johnson_counter dut (
    .clock(clock),
    .reset(reset),
    .counter_state(counter_state)
);

// Parameters
parameter SIMULATION_CYCLES = 100; // Adjust this value as needed



initial begin

     $dumpfile("johnson_counter.vcd");
    $dumpvars(0, johnson_counter_tb); 
    
          

end



// Clock generation
initial begin
    clock = 0;
    forever #5 clock = ~clock;
end

// Reset generation
initial begin
    reset = 1;
    #10 reset = 0;
    #20 reset = 1;
    #30 reset = 0;
    // Add more reset pulses as needed
end

// Monitor for observing the counter state changes
always @(posedge clock) begin
    $display("Counter State: %b", counter_state);
    
    // Stop the simulation after SIMULATION_CYCLES clock cycles
    if ($time >= SIMULATION_CYCLES * 10) // Assuming each clock period is 10 time units
        $finish;
end

endmodule

question 3/johnson_counter.vcd
$date
	Mon Aug 14 22:59:53 2023
$end
$version
	Icarus Verilog
$end
$timescale
	1ns
$end
$scope module johnson_counter_tb $end
$var wire 4 ! counter_state [3:0] $end
$var parameter 32 " SIMULATION_CYCLES $end
$var reg 1 # clock $end
$var reg 1 $ reset $end
$scope module dut $end
$var wire 1 # clock $end
$var wire 4 % counter_state [3:0] $end
$var wire 1 $ reset $end
$var reg 4 & counter [3:0] $end
$upscope $end
$upscope $end
$enddefinitions $end
$comment Show the parameter values. $end
$dumpall
b1100100 "
$end
#0
$dumpvars
b0 &
b0 %
1$
0#
b0 !
$end
#5
1#
#10
0#
0$
#15
b1 !
b1 %
b1 &
1#
#20
0#
#25
b11 !
b11 %
b11 &
1#
#30
b0 !
b0 %
b0 &
0#
1$
#35
1#
#40
0#
#45
1#
#50
0#
#55
1#
#60
0#
0$
#65
b1 !
b1 %
b1 &
1#
#70
0#
#75
b11 !
b11 %
b11 &
1#
#80
0#
#85
b111 !
b111 %
b111 &
1#
#90
0#
#95
b1111 !
b1111 %
b1111 &
1#
#100
0#
#105
b1110 !
b1110 %
b1110 &
1#
#110
0#
#115
b1100 !
b1100 %
b1100 &
1#
#120
0#
#125
b1000 !
b1000 %
b1000 &
1#
#130
0#
#135
b0 !
b0 %
b0 &
1#
#140
0#
#145
b1 !
b1 %
b1 &
1#
#150
0#
#155
b11 !
b11 %
b11 &
1#
#160
0#
#165
b111 !
b111 %
b111 &
1#
#170
0#
#175
b1111 !
b1111 %
b1111 &
1#
#180
0#
#185
b1110 !
b1110 %
b1110 &
1#
#190
0#
#195
b1100 !
b1100 %
b1100 &
1#
#200
0#
#205
b1000 !
b1000 %
b1000 &
1#
#210
0#
#215
b0 !
b0 %
b0 &
1#
#220
0#
#225
b1 !
b1 %
b1 &
1#
#230
0#
#235
b11 !
b11 %
b11 &
1#
#240
0#
#245
b111 !
b111 %
b111 &
1#
#250
0#
#255
b1111 !
b1111 %
b1111 &
1#
#260
0#
#265
b1110 !
b1110 %
b1110 &
1#
#270
0#
#275
b1100 !
b1100 %
b1100 &
1#
#280
0#
#285
b1000 !
b1000 %
b1000 &
1#
#290
0#
#295
b0 !
b0 %
b0 &
1#
#300
0#
#305
b1 !
b1 %
b1 &
1#
#310
0#
#315
b11 !
b11 %
b11 &
1#
#320
0#
#325
b111 !
b111 %
b111 &
1#
#330
0#
#335
b1111 !
b1111 %
b1111 &
1#
#340
0#
#345
b1110 !
b1110 %
b1110 &
1#
#350
0#
#355
b1100 !
b1100 %
b1100 &
1#
#360
0#
#365
b1000 !
b1000 %
b1000 &
1#
#370
0#
#375
b0 !
b0 %
b0 &
1#
#380
0#
#385
b1 !
b1 %
b1 &
1#
#390
0#
#395
b11 !
b11 %
b11 &
1#
#400
0#
#405
b111 !
b111 %
b111 &
1#
#410
0#
#415
b1111 !
b1111 %
b1111 &
1#
#420
0#
#425
b1110 !
b1110 %
b1110 &
1#
#430
0#
#435
b1100 !
b1100 %
b1100 &
1#
#440
0#
#445
b1000 !
b1000 %
b1000 &
1#
#450
0#
#455
b0 !
b0 %
b0 &
1#
#460
0#
#465
b1 !
b1 %
b1 &
1#
#470
0#
#475
b11 !
b11 %
b11 &
1#
#480
0#
#485
b111 !
b111 %
b111 &
1#
#490
0#
#495
b1111 !
b1111 %
b1111 &
1#
#500
0#
#505
b1110 !
b1110 %
b1110 &
1#
#510
0#
#515
b1100 !
b1100 %
b1100 &
1#
#520
0#
#525
b1000 !
b1000 %
b1000 &
1#
#530
0#
#535
b0 !
b0 %
b0 &
1#
#540
0#
#545
b1 !
b1 %
b1 &
1#
#550
0#
#555
b11 !
b11 %
b11 &
1#
#560
0#
#565
b111 !
b111 %
b111 &
1#
#570
0#
#575
b1111 !
b1111 %
b1111 &
1#
#580
0#
#585
b1110 !
b1110 %
b1110 &
1#
#590
0#
#595
b1100 !
b1100 %
b1100 &
1#
#600
0#
#605
b1000 !
b1000 %
b1000 &
1#
#610
0#
#615
b0 !
b0 %
b0 &
1#
#620
0#
#625
b1 !
b1 %
b1 &
1#
#630
0#
#635
b11 !
b11 %
b11 &
1#
#640
0#
#645
b111 !
b111 %
b111 &
1#
#650
0#
#655
b1111 !
b1111 %
b1111 &
1#
#660
0#
#665
b1110 !
b1110 %
b1110 &
1#
#670
0#
#675
b1100 !
b1100 %
b1100 &
1#
#680
0#
#685
b1000 !
b1000 %
b1000 &
1#
#690
0#
#695
b0 !
b0 %
b0 &
1#
#700
0#
#705
b1 !
b1 %
b1 &
1#
#710
0#
#715
b11 !
b11 %
b11 &
1#
#720
0#
#725
b111 !
b111 %
b111 &
1#
#730
0#
#735
b1111 !
b1111 %
b1111 &
1#
#740
0#
#745
b1110 !
b1110 %
b1110 &
1#
#750
0#
#755
b1100 !
b1100 %
b1100 &
1#
#760
0#
#765
b1000 !
b1000 %
b1000 &
1#
#770
0#
#775
b0 !
b0 %
b0 &
1#
#780
0#
#785
b1 !
b1 %
b1 &
1#
#790
0#
#795
b11 !
b11 %
b11 &
1#
#800
0#
#805
b111 !
b111 %
b111 &
1#
#810
0#
#815
b1111 !
b1111 %
b1111 &
1#
#820
0#
#825
b1110 !
b1110 %
b1110 &
1#
#830
0#
#835
b1100 !
b1100 %
b1100 &
1#
#840
0#
#845
b1000 !
b1000 %
b1000 &
1#
#850
0#
#855
b0 !
b0 %
b0 &
1#
#860
0#
#865
b1 !
b1 %
b1 &
1#
#870
0#
#875
b11 !
b11 %
b11 &
1#
#880
0#
#885
b111 !
b111 %
b111 &
1#
#890
0#
#895
b1111 !
b1111 %
b1111 &
1#
#900
0#
#905
b1110 !
b1110 %
b1110 &
1#
#910
0#
#915
b1100 !
b1100 %
b1100 &
1#
#920
0#
#925
b1000 !
b1000 %
b1000 &
1#
#930
0#
#935
b0 !
b0 %
b0 &
1#
#940
0#
#945
b1 !
b1 %
b1 &
1#
#950
0#
#955
b11 !
b11 %
b11 &
1#
#960
0#
#965
b111 !
b111 %
b111 &
1#
#970
0#
#975
b1111 !
b1111 %
b1111 &
1#
#980
0#
#985
b1110 !
b1110 %
b1110 &
1#
#990
0#
#995
b1100 !
b1100 %
b1100 &
1#
#1000
0#
#1005
b1000 !
b1000 %
b1000 &
1#
